casbin_redis_watcher/__init__.py
casbin_redis_watcher/options.py
casbin_redis_watcher/watcher.py
node_modules/npm/node_modules/node-gyp/gyp/gyp_main.py
node_modules/npm/node_modules/node-gyp/gyp/test_gyp.py
node_modules/npm/node_modules/node-gyp/gyp/pylib/gyp/MSVSNew.py
node_modules/npm/node_modules/node-gyp/gyp/pylib/gyp/MSVSProject.py
node_modules/npm/node_modules/node-gyp/gyp/pylib/gyp/MSVSSettings.py
node_modules/npm/node_modules/node-gyp/gyp/pylib/gyp/MSVSSettings_test.py
node_modules/npm/node_modules/node-gyp/gyp/pylib/gyp/MSVSToolFile.py
node_modules/npm/node_modules/node-gyp/gyp/pylib/gyp/MSVSUserFile.py
node_modules/npm/node_modules/node-gyp/gyp/pylib/gyp/MSVSUtil.py
node_modules/npm/node_modules/node-gyp/gyp/pylib/gyp/MSVSVersion.py
node_modules/npm/node_modules/node-gyp/gyp/pylib/gyp/__init__.py
node_modules/npm/node_modules/node-gyp/gyp/pylib/gyp/common.py
node_modules/npm/node_modules/node-gyp/gyp/pylib/gyp/common_test.py
node_modules/npm/node_modules/node-gyp/gyp/pylib/gyp/easy_xml.py
node_modules/npm/node_modules/node-gyp/gyp/pylib/gyp/easy_xml_test.py
node_modules/npm/node_modules/node-gyp/gyp/pylib/gyp/flock_tool.py
node_modules/npm/node_modules/node-gyp/gyp/pylib/gyp/input.py
node_modules/npm/node_modules/node-gyp/gyp/pylib/gyp/input_test.py
node_modules/npm/node_modules/node-gyp/gyp/pylib/gyp/mac_tool.py
node_modules/npm/node_modules/node-gyp/gyp/pylib/gyp/msvs_emulation.py
node_modules/npm/node_modules/node-gyp/gyp/pylib/gyp/ninja_syntax.py
node_modules/npm/node_modules/node-gyp/gyp/pylib/gyp/simple_copy.py
node_modules/npm/node_modules/node-gyp/gyp/pylib/gyp/win_tool.py
node_modules/npm/node_modules/node-gyp/gyp/pylib/gyp/xcode_emulation.py
node_modules/npm/node_modules/node-gyp/gyp/pylib/gyp/xcode_ninja.py
node_modules/npm/node_modules/node-gyp/gyp/pylib/gyp/xcodeproj_file.py
node_modules/npm/node_modules/node-gyp/gyp/pylib/gyp/xml_fix.py
node_modules/npm/node_modules/node-gyp/gyp/pylib/gyp/generator/__init__.py
casbin_redis_watcher-1.3.0.dist-info/LICENSE
casbin_redis_watcher-1.3.0.dist-info/METADATA
casbin_redis_watcher-1.3.0.dist-info/WHEEL
casbin_redis_watcher-1.3.0.dist-info/top_level.txt
casbin_redis_watcher-1.3.0.dist-info/RECORD
