Metadata-Version: 2.1
Name: casbin-redis-watcher
Version: 1.3.0
Summary: Casbin role watcher to be used for monitoring updates to policies for PyCasbin
Author-email: nekotoxin <nekotoxin@gmail.com>
License: Apache 2.0
Project-URL: Home-page, https://github.com/pycasbin/redis-watcher
Classifier: Programming Language :: Python :: 3.9
Classifier: Programming Language :: Python :: 3.10
Classifier: Programming Language :: Python :: 3.11
Classifier: Programming Language :: Python :: 3.12
Classifier: License :: OSI Approved :: Apache Software License
Classifier: Operating System :: OS Independent
License-File: LICENSE
Requires-Dist: casbin ~=1.18
Requires-Dist: redis ==4.5.2
